{"path":"%D0%A2%D0%B0%D1%84%D1%80%D0%B8%D0%BD%D0%B0%20%D1%87%D0%B5%D1%80%D1%91%D0%BC%D1%83%D1%85%D0%BE%D0%B2%D0%B0%D1%8F%20%28Taphrina%20padi%29","deepCounters":{"total":8,"images":8,"files":8},"counters":{"total":8,"images":8,"files":8},"thumb":{"path":"thumbs\/DSC08041.JPG","width":426,"height":320},"thumbCaption":"<h3>Тафрина черёмуховая (Taphrina padi)<\/h3>","album":{"description":"Fungarium.INFO. Fungarium Photo Collection: Boletes, Toadstools, Agarics, Fungi, Molds and Myxomycetes.\n<br\/><br\/>\n<i><b>313<\/b> species in <b>84<\/b> families photographed.<br\/>\n<b>2806<\/b> images total.<\/i><br\/>","title":"Fungarium.INFO Fungi"},"objects":[{"image":{"path":"slides\/DSC08038.JPG","width":768,"height":1024},"thumb":{"path":"thumbs\/DSC08038.JPG","width":426,"height":320},"thumbCaption":"<span class=\"nr\">1<\/span>  <small>                               <\/small>","photodata":"<p><b>Original Date<\/b> <i>6\/9\/17 2:15 PM<\/i><\/p><p><b>Camera<\/b> <i>DSC-HX90<\/i><\/p><p><b>Focal Length (35mm)<\/b> <i>75mm<\/i><\/p><p><b>Metering Mode<\/b> <i>Multi-segment<\/i><\/p><p><b>ISO Equivalent<\/b> <i>100<\/i><\/p><p><b>Exposure Time<\/b> <i>1\/500s<\/i><\/p><p><b>Aperture<\/b> <i>5<\/i><\/p><p><b>Exposure bias<\/b> <i>0 EV<\/i><\/p><p><b>Exposure Program<\/b> <i>Manual control<\/i><\/p><p><b>White balance<\/b> <i>Manual white balance<\/i><\/p><p><b>Flash<\/b> <i>Flash did not fire, auto<\/i><\/p><p><b>Resolution<\/b> <i>4896 x 3672<\/i><\/p>","fileDate":"2017-06-09T14:15:28.0Z","modifiedDays":17332.0,"path":"DSC08038.JPG","imageCaption":"<h5>DSC08038<\/h5><div class=\"comment\">                               <\/div>","fileSize":5661308,"epochDate":1.497006929E12,"name":"DSC08038.JPG","comment":"                               ","category":"image","camera":{"aperture":5.0,"exposureTime":"1\/500s","originalDate":"2017-06-09T14:15:29.0Z","cameraModel":"DSC-HX90","focalLength35mm":"75mm","resolution":"4896 x 3672","cameraMake":"SONY","isoEquivalent":100,"flash":"Flash did not fire, auto","focalLength":"13mm"}},{"image":{"path":"slides\/DSC08039.JPG","width":768,"height":1024},"thumb":{"path":"thumbs\/DSC08039.JPG","width":426,"height":320},"thumbCaption":"<span class=\"nr\">2<\/span>  <small>                               <\/small>","photodata":"<p><b>Original Date<\/b> <i>6\/9\/17 2:15 PM<\/i><\/p><p><b>Camera<\/b> <i>DSC-HX90<\/i><\/p><p><b>Focal Length (35mm)<\/b> <i>43mm<\/i><\/p><p><b>Metering Mode<\/b> <i>Multi-segment<\/i><\/p><p><b>ISO Equivalent<\/b> <i>100<\/i><\/p><p><b>Exposure Time<\/b> <i>1\/800s<\/i><\/p><p><b>Aperture<\/b> <i>4<\/i><\/p><p><b>Exposure bias<\/b> <i>0 EV<\/i><\/p><p><b>Exposure Program<\/b> <i>Manual control<\/i><\/p><p><b>White balance<\/b> <i>Manual white balance<\/i><\/p><p><b>Flash<\/b> <i>Flash did not fire, auto<\/i><\/p><p><b>Resolution<\/b> <i>4896 x 3672<\/i><\/p>","fileDate":"2017-06-09T14:15:42.0Z","modifiedDays":17332.0,"path":"DSC08039.JPG","imageCaption":"<h5>DSC08039<\/h5><div class=\"comment\">                               <\/div>","fileSize":5368056,"epochDate":1.497006943E12,"name":"DSC08039.JPG","comment":"                               ","category":"image","camera":{"aperture":4.0,"exposureTime":"1\/800s","originalDate":"2017-06-09T14:15:43.0Z","cameraModel":"DSC-HX90","focalLength35mm":"43mm","resolution":"4896 x 3672","cameraMake":"SONY","isoEquivalent":100,"flash":"Flash did not fire, auto","focalLength":"7mm"}},{"image":{"path":"slides\/DSC08040.JPG","width":1024,"height":768},"thumb":{"path":"thumbs\/DSC08040.JPG","width":426,"height":320},"thumbCaption":"<span class=\"nr\">3<\/span>  <small>                               <\/small>","photodata":"<p><b>Original Date<\/b> <i>6\/9\/17 2:15 PM<\/i><\/p><p><b>Camera<\/b> <i>DSC-HX90<\/i><\/p><p><b>Focal Length (35mm)<\/b> <i>43mm<\/i><\/p><p><b>Metering Mode<\/b> <i>Multi-segment<\/i><\/p><p><b>ISO Equivalent<\/b> <i>100<\/i><\/p><p><b>Exposure Time<\/b> <i>1\/800s<\/i><\/p><p><b>Aperture<\/b> <i>4<\/i><\/p><p><b>Exposure bias<\/b> <i>0 EV<\/i><\/p><p><b>Exposure Program<\/b> <i>Manual control<\/i><\/p><p><b>White balance<\/b> <i>Manual white balance<\/i><\/p><p><b>Flash<\/b> <i>Flash did not fire, auto<\/i><\/p><p><b>Resolution<\/b> <i>4896 x 3672<\/i><\/p>","fileDate":"2017-06-09T14:15:50.0Z","modifiedDays":17332.0,"path":"DSC08040.JPG","imageCaption":"<h5>DSC08040<\/h5><div class=\"comment\">                               <\/div>","fileSize":5798008,"epochDate":1.49700695E12,"name":"DSC08040.JPG","comment":"                               ","category":"image","camera":{"aperture":4.0,"exposureTime":"1\/800s","originalDate":"2017-06-09T14:15:50.0Z","cameraModel":"DSC-HX90","focalLength35mm":"43mm","resolution":"4896 x 3672","cameraMake":"SONY","isoEquivalent":100,"flash":"Flash did not fire, auto","focalLength":"7mm"}},{"image":{"path":"slides\/DSC08041.JPG","width":1024,"height":768},"thumb":{"path":"thumbs\/DSC08041.JPG","width":426,"height":320},"thumbCaption":"<span class=\"nr\">4<\/span>  <small>                               <\/small>","photodata":"<p><b>Original Date<\/b> <i>6\/9\/17 2:16 PM<\/i><\/p><p><b>Camera<\/b> <i>DSC-HX90<\/i><\/p><p><b>Focal Length (35mm)<\/b> <i>43mm<\/i><\/p><p><b>Metering Mode<\/b> <i>Multi-segment<\/i><\/p><p><b>ISO Equivalent<\/b> <i>400<\/i><\/p><p><b>Exposure Time<\/b> <i>1\/640s<\/i><\/p><p><b>Aperture<\/b> <i>4<\/i><\/p><p><b>Exposure bias<\/b> <i>0 EV<\/i><\/p><p><b>Exposure Program<\/b> <i>Manual control<\/i><\/p><p><b>White balance<\/b> <i>Manual white balance<\/i><\/p><p><b>Flash<\/b> <i>Flash did not fire, auto<\/i><\/p><p><b>Resolution<\/b> <i>4896 x 3672<\/i><\/p>","fileDate":"2017-06-09T14:16:15.999Z","modifiedDays":17332.0,"path":"DSC08041.JPG","imageCaption":"<h5>DSC08041<\/h5><div class=\"comment\">                               <\/div>","fileSize":6496234,"epochDate":1.497006977E12,"name":"DSC08041.JPG","comment":"                               ","category":"image","camera":{"aperture":4.0,"exposureTime":"1\/640s","originalDate":"2017-06-09T14:16:17.0Z","cameraModel":"DSC-HX90","focalLength35mm":"43mm","resolution":"4896 x 3672","cameraMake":"SONY","isoEquivalent":400,"flash":"Flash did not fire, auto","focalLength":"7mm"}},{"image":{"path":"slides\/DSC08042.JPG","width":768,"height":1024},"thumb":{"path":"thumbs\/DSC08042.JPG","width":426,"height":320},"thumbCaption":"<span class=\"nr\">5<\/span>  <small>                               <\/small>","photodata":"<p><b>Original Date<\/b> <i>6\/9\/17 2:16 PM<\/i><\/p><p><b>Camera<\/b> <i>DSC-HX90<\/i><\/p><p><b>Focal Length (35mm)<\/b> <i>43mm<\/i><\/p><p><b>Metering Mode<\/b> <i>Multi-segment<\/i><\/p><p><b>ISO Equivalent<\/b> <i>400<\/i><\/p><p><b>Exposure Time<\/b> <i>1\/400s<\/i><\/p><p><b>Aperture<\/b> <i>4<\/i><\/p><p><b>Exposure bias<\/b> <i>0 EV<\/i><\/p><p><b>Exposure Program<\/b> <i>Manual control<\/i><\/p><p><b>White balance<\/b> <i>Manual white balance<\/i><\/p><p><b>Flash<\/b> <i>Flash did not fire, auto<\/i><\/p><p><b>Resolution<\/b> <i>4896 x 3672<\/i><\/p>","fileDate":"2017-06-09T14:16:36.0Z","modifiedDays":17332.0,"path":"DSC08042.JPG","imageCaption":"<h5>DSC08042<\/h5><div class=\"comment\">                               <\/div>","fileSize":6414342,"epochDate":1.497006997E12,"name":"DSC08042.JPG","comment":"                               ","category":"image","camera":{"aperture":4.0,"exposureTime":"1\/400s","originalDate":"2017-06-09T14:16:37.0Z","cameraModel":"DSC-HX90","focalLength35mm":"43mm","resolution":"4896 x 3672","cameraMake":"SONY","isoEquivalent":400,"flash":"Flash did not fire, auto","focalLength":"7mm"}},{"image":{"path":"slides\/DSC08043.JPG","width":768,"height":1024},"thumb":{"path":"thumbs\/DSC08043.JPG","width":426,"height":320},"thumbCaption":"<span class=\"nr\">6<\/span>  <small>                               <\/small>","photodata":"<p><b>Original Date<\/b> <i>6\/9\/17 2:17 PM<\/i><\/p><p><b>Camera<\/b> <i>DSC-HX90<\/i><\/p><p><b>Focal Length (35mm)<\/b> <i>43mm<\/i><\/p><p><b>Metering Mode<\/b> <i>Multi-segment<\/i><\/p><p><b>ISO Equivalent<\/b> <i>400<\/i><\/p><p><b>Exposure Time<\/b> <i>1\/1250s<\/i><\/p><p><b>Aperture<\/b> <i>4<\/i><\/p><p><b>Exposure bias<\/b> <i>0 EV<\/i><\/p><p><b>Exposure Program<\/b> <i>Manual control<\/i><\/p><p><b>White balance<\/b> <i>Manual white balance<\/i><\/p><p><b>Flash<\/b> <i>Flash did not fire, auto<\/i><\/p><p><b>Resolution<\/b> <i>4896 x 3672<\/i><\/p>","fileDate":"2017-06-09T14:16:59.999Z","modifiedDays":17332.0,"path":"DSC08043.JPG","imageCaption":"<h5>DSC08043<\/h5><div class=\"comment\">                               <\/div>","fileSize":4774876,"epochDate":1.497007021E12,"name":"DSC08043.JPG","comment":"                               ","category":"image","camera":{"aperture":4.0,"exposureTime":"1\/1250s","originalDate":"2017-06-09T14:17:01.0Z","cameraModel":"DSC-HX90","focalLength35mm":"43mm","resolution":"4896 x 3672","cameraMake":"SONY","isoEquivalent":400,"flash":"Flash did not fire, auto","focalLength":"7mm"}},{"image":{"path":"slides\/DSC08044.JPG","width":768,"height":1024},"thumb":{"path":"thumbs\/DSC08044.JPG","width":426,"height":320},"thumbCaption":"<span class=\"nr\">7<\/span>  <small>                               <\/small>","photodata":"<p><b>Original Date<\/b> <i>6\/9\/17 2:17 PM<\/i><\/p><p><b>Camera<\/b> <i>DSC-HX90<\/i><\/p><p><b>Focal Length (35mm)<\/b> <i>43mm<\/i><\/p><p><b>Metering Mode<\/b> <i>Multi-segment<\/i><\/p><p><b>ISO Equivalent<\/b> <i>200<\/i><\/p><p><b>Exposure Time<\/b> <i>1\/800s<\/i><\/p><p><b>Aperture<\/b> <i>4<\/i><\/p><p><b>Exposure bias<\/b> <i>0 EV<\/i><\/p><p><b>Exposure Program<\/b> <i>Manual control<\/i><\/p><p><b>White balance<\/b> <i>Manual white balance<\/i><\/p><p><b>Flash<\/b> <i>Flash did not fire, auto<\/i><\/p><p><b>Resolution<\/b> <i>4896 x 3672<\/i><\/p>","fileDate":"2017-06-09T14:17:15.999Z","modifiedDays":17332.0,"path":"DSC08044.JPG","imageCaption":"<h5>DSC08044<\/h5><div class=\"comment\">                               <\/div>","fileSize":5052586,"epochDate":1.497007036E12,"name":"DSC08044.JPG","comment":"                               ","category":"image","camera":{"aperture":4.0,"exposureTime":"1\/800s","originalDate":"2017-06-09T14:17:16.0Z","cameraModel":"DSC-HX90","focalLength35mm":"43mm","resolution":"4896 x 3672","cameraMake":"SONY","isoEquivalent":200,"flash":"Flash did not fire, auto","focalLength":"7mm"}},{"image":{"path":"slides\/DSC08045.JPG","width":768,"height":1024},"thumb":{"path":"thumbs\/DSC08045.JPG","width":426,"height":320},"thumbCaption":"<span class=\"nr\">8<\/span>  <small>                               <\/small>","photodata":"<p><b>Original Date<\/b> <i>6\/9\/17 2:17 PM<\/i><\/p><p><b>Camera<\/b> <i>DSC-HX90<\/i><\/p><p><b>Focal Length (35mm)<\/b> <i>43mm<\/i><\/p><p><b>Metering Mode<\/b> <i>Multi-segment<\/i><\/p><p><b>ISO Equivalent<\/b> <i>200<\/i><\/p><p><b>Exposure Time<\/b> <i>1\/1000s<\/i><\/p><p><b>Aperture<\/b> <i>4<\/i><\/p><p><b>Exposure bias<\/b> <i>0 EV<\/i><\/p><p><b>Exposure Program<\/b> <i>Manual control<\/i><\/p><p><b>White balance<\/b> <i>Manual white balance<\/i><\/p><p><b>Flash<\/b> <i>Flash did not fire, auto<\/i><\/p><p><b>Resolution<\/b> <i>4896 x 3672<\/i><\/p>","fileDate":"2017-06-09T14:17:28.0Z","modifiedDays":17332.0,"path":"DSC08045.JPG","imageCaption":"<h5>DSC08045<\/h5><div class=\"comment\">                               <\/div>","fileSize":6613739,"epochDate":1.497007049E12,"name":"DSC08045.JPG","comment":"                               ","category":"image","camera":{"aperture":4.0,"exposureTime":"1\/1000s","originalDate":"2017-06-09T14:17:29.0Z","cameraModel":"DSC-HX90","focalLength35mm":"43mm","resolution":"4896 x 3672","cameraMake":"SONY","isoEquivalent":200,"flash":"Flash did not fire, auto","focalLength":"7mm"}}],"name":"Тафрина черёмуховая (Taphrina padi)","epochDateRange":"1497006929000,1497007049000","fileDate":"2017-06-17T20:18:02.192Z","modifiedDays":17332.0}